<?xml version="1.0" encoding="utf-8"?>
<odoo>
    <data noupdate="1">

        <record id="partner_bca_holding" model="res.partner">
            <field name="name">Grupo BCA</field>
            <field name="is_company" eval="True"/>
            <field name="bca_tipo">holding</field>
        </record>

        <record id="partner_metlife" model="res.partner">
            <field name="name">MetLife México</field>
            <field name="is_company" eval="True"/>
            <field name="bca_tipo">aseguradora</field>
            <field name="bca_codigo_aseguradora">METLIFE</field>
        </record>

        <record id="partner_qualitas" model="res.partner">
            <field name="name">Quálitas Compañía de Seguros</field>
            <field name="is_company" eval="True"/>
            <field name="bca_tipo">aseguradora</field>
            <field name="bca_codigo_aseguradora">QUALITAS</field>
        </record>

    </data>
</odoo>
